hetman_pipeline_plugin_i18n-1.0.3.dist-info/licenses/LICENSE
pipeline_plugin_i18n/__init__.py
pipeline_plugin_i18n/patch.py
pipeline_plugin_i18n/plugin.py
pipeline_plugin_i18n/resources/exceptions.py
pipeline_plugin_i18n/resources/types.py
hetman_pipeline_plugin_i18n-1.0.3.dist-info/METADATA
hetman_pipeline_plugin_i18n-1.0.3.dist-info/WHEEL
hetman_pipeline_plugin_i18n-1.0.3.dist-info/top_level.txt
hetman_pipeline_plugin_i18n-1.0.3.dist-info/RECORD
