Metadata-Version: 2.4
Name: hetman-pipeline-plugin-i18n
Version: 1.0.3
Summary: Hetman Pipeline Plugin I18n is a plugin for Hetman Pipeline that provides i18n support.
Author-email: Hetman <degadupeko@my-relay.app>
Project-URL: Homepage, https://pipeline.hetman.app
Project-URL: Documentation, https://github.com/hetman-app/hetman-pipeline-plugin-i18n
Project-URL: Repository, https://github.com/hetman-app/hetman-pipeline-plugin-i18n
Project-URL: Issues, https://github.com/hetman-app/hetman-pipeline-plugin-i18n/issues
Classifier: Programming Language :: Python :: 3.10
Classifier: Programming Language :: Python :: 3.11
Classifier: Programming Language :: Python :: 3.12
Classifier: Programming Language :: Python :: 3.13
Classifier: Programming Language :: Python :: 3.14
Requires-Python: >=3.10
License-File: LICENSE
Requires-Dist: hetman-pipeline>=2.2.2
Requires-Dist: hetman-kit-localize>=1.0.0
Dynamic: license-file
